opptimizer/Executor.py
opptimizer/Mod.py
opptimizer/PExecutable.py
opptimizer/PExecutor.py
opptimizer/PLog.py
opptimizer/PModule.py
opptimizer/PModulePy.py
opptimizer/PObject.py
opptimizer/PPath.py
opptimizer/PResult.py
opptimizer/PScript.py
opptimizer/PTest.py
opptimizer/Token.py
opptimizer/__about__.py
opptimizer/__init__.py
opptimizer/opp.py
opptimizer/pcons.py
opptimizer/pmodutils.py
opptimizer/putils.py
opptimizer/version.txt
opptimizer-2.3.8.dist-info/LICENSE
opptimizer-2.3.8.dist-info/METADATA
opptimizer-2.3.8.dist-info/WHEEL
opptimizer-2.3.8.dist-info/RECORD
