Metadata-Version: 2.1
Name: opptimizer
Version: 2.3.8
Summary: Optimization of hyperparameters for Machine Learning (AI)
Home-page: https://github.com/virtgen/opptimizer
License: Apache-2.0
Author: Artur Bąk
Author-email: virtgen@gmail.com
Requires-Python: >=3.8,<4.0
Classifier: License :: OSI Approved :: Apache Software License
Classifier: Programming Language :: Python :: 3
Classifier: Programming Language :: Python :: 3.8
Classifier: Programming Language :: Python :: 3.9
Classifier: Programming Language :: Python :: 3.10
Classifier: Programming Language :: Python :: 3.11
Classifier: Programming Language :: Python :: 3.12
Requires-Dist: matplotlib (>=3.5,<4.0)
